__init__.py
app/__init__.py
app/main.py
app/controller/__init__.py
app/controller/commandlinecontroller.py
app/generators/envgenerator.py
app/generators/filegenerator.py
app/generators/foldergenerator.py
pyproject_initializr-1.0.1.dist-info/LICENSE
pyproject_initializr-1.0.1.dist-info/METADATA
pyproject_initializr-1.0.1.dist-info/WHEEL
pyproject_initializr-1.0.1.dist-info/entry_points.txt
pyproject_initializr-1.0.1.dist-info/top_level.txt
pyproject_initializr-1.0.1.dist-info/RECORD
