Metadata-Version: 2.1
Name: pyproject-initializr
Version: 1.0.1
Summary: Creates a project directory with some helpful default files and directories
Author-email: ans2ur <ans2urgt@gmail.com>
License: Copyright (c) 2018 The Python Packaging Authority
Project-URL: Homepage, https://github.com/ans2urgt/PyProjectInitializr
Keywords: python,project,initializer
Classifier: Programming Language :: Python :: 3
Classifier: License :: OSI Approved :: MIT License
Classifier: Operating System :: OS Independent
License-File: LICENSE
